mgzip/__init__.py
mgzip/__main__.py
mgzip/multiProcGzip.py
usc_isi_i2_mgzip-0.2.1.3.dist-info/LICENSE
usc_isi_i2_mgzip-0.2.1.3.dist-info/METADATA
usc_isi_i2_mgzip-0.2.1.3.dist-info/WHEEL
usc_isi_i2_mgzip-0.2.1.3.dist-info/top_level.txt
usc_isi_i2_mgzip-0.2.1.3.dist-info/RECORD
