Metadata-Version: 2.1
Name: usc-isi-i2-mgzip
Version: 0.2.1.3
Summary: A multi-threading implementation of Python gzip module, based on the work of Vincent Li.
Home-page: https://github.com/usc-isi-i2/mgzip
Author: Craig Milo Rogers
Author-email: CraigMiloRogers@gmail.com
License: MIT
Platform: UNKNOWN
Classifier: Development Status :: 4 - Beta
Classifier: License :: OSI Approved :: MIT License
Classifier: Operating System :: OS Independent
Classifier: Programming Language :: Python :: 3
Classifier: Programming Language :: Python :: Implementation :: CPython
Classifier: Topic :: Software Development :: Libraries :: Python Modules
Classifier: Intended Audience :: Developers
Requires-Python: >=3.6
License-File: LICENSE
